declareamqp
