Metadata-Version: 1.0
Name: declare-amqp
Version: 0.0.2
Summary: A way to declare your AMQP exchanges, queues, and bindings outside of the application
Home-page: http://github.com/philipcristiano/declare-amqp
Author: Philip Cristiano
Author-email: philipcristiano@gmail.com
License: BSD
Keywords: amqp
Platform: UNKNOWN
